proj1_make/TOP/RTL/uart_tx.v
`timescale 1ns / 1ps

module uart_tx (
    //port list
    clk             ,
    rst_n           ,

    i_tx_data       ,
    i_tx_start      ,

    o_tx            ,
    o_tx_busy       ,
    o_tx_done    
);

// port declaration
input           clk         ;
input           rst_n       ;
input   [7:0]   i_tx_data   ;
input           i_tx_start  ;

output          o_tx        ;
output          o_tx_busy   ;
output          o_tx_done   ;

// parameter
parameter CLKS_PER_BIT    =   417;

// state parameter
localparam IDLE = 2'b00;
localparam START = 2'b01;
localparam DATA = 2'b10;
localparam STOP = 2'b11;

// internal register

reg     [1:0]   r_state     ;

reg     [8:0]   r_baud_cnt  ;
reg     [2:0]   r_bit_cnt   ;

reg     [7:0]   r_tx_data   ;

reg             r_tx        ;
reg             r_tx_busy   ;
reg             r_tx_done   ;


// modeling
always @(posedge clk or negedge rst_n) begin

    if( ~rst_n ) begin

        r_state     <= IDLE     ;

        r_baud_cnt  <= 9'd0     ;
        r_bit_cnt   <= 3'd0     ;

        r_tx_data   <= 8'd0     ;

        r_tx        <= 1'b1     ;
        r_tx_busy   <= 1'b0     ;
        r_tx_done   <= 1'b0     ;

    end
    else begin

        case( r_state )

            // ------------------------------------------------
            // IDLE
            // UART line stays HIGH
            // Wait for i_tx_start
            // ------------------------------------------------

            IDLE : begin

                r_tx        <= 1'b1     ;
                r_tx_busy   <= 1'b0     ;
                r_tx_done   <= 1'b0     ;

                r_baud_cnt  <= 9'd0     ;
                r_bit_cnt   <= 3'd0     ;

                if( i_tx_start ) begin

                    r_tx_data   <= i_tx_data  ;
                    r_tx_busy   <= 1'b1       ;
                    r_state     <= START      ;

                end

            end


            // ------------------------------------------------
            // START BIT
            // TX = 0 for one bit period
            // ------------------------------------------------

            START : begin

                r_tx        <= 1'b0     ;
                r_tx_busy   <= 1'b1     ;
                r_tx_done   <= 1'b0     ;

                if( r_baud_cnt == CLKS_PER_BIT - 1 ) begin

                    r_baud_cnt  <= 9'd0 ;
                    r_state     <= DATA ;

                end
                else begin

                    r_baud_cnt  <= r_baud_cnt + 1'b1;

                end

            end


            // ------------------------------------------------
            // DATA
            // Send 8-bit data
            // LSB first
            // ------------------------------------------------

            DATA : begin

                r_tx        <= r_tx_data[r_bit_cnt] ;
                r_tx_busy   <= 1'b1                 ;
                r_tx_done   <= 1'b0                 ;

                if( r_baud_cnt == CLKS_PER_BIT - 1 ) begin

                    r_baud_cnt <= 9'd0;

                    if( r_bit_cnt == 3'd7 ) begin

                        r_bit_cnt <= 3'd0;
                        r_state   <= STOP;

                    end
                    else begin

                        r_bit_cnt <= r_bit_cnt + 1'b1;

                    end

                end
                else begin

                    r_baud_cnt <= r_baud_cnt + 1'b1;

                end

            end


            // ------------------------------------------------
            // STOP BIT
            // TX = 1 for one bit period
            // ------------------------------------------------

            STOP : begin

                r_tx        <= 1'b1     ;
                r_tx_busy   <= 1'b1     ;
                r_tx_done   <= 1'b0     ;

                if( r_baud_cnt == CLKS_PER_BIT - 1 ) begin

                    r_baud_cnt  <= 9'd0     ;

                    r_tx_busy   <= 1'b0     ;
                    r_tx_done   <= 1'b1     ;

                    r_state     <= IDLE     ;

                end
                else begin

                    r_baud_cnt <= r_baud_cnt + 1'b1;

                end

            end


            // ------------------------------------------------
            // DEFAULT
            // ------------------------------------------------

            default : begin

                r_state     <= IDLE     ;

                r_baud_cnt  <= 9'd0     ;
                r_bit_cnt   <= 3'd0     ;

                r_tx        <= 1'b1     ;
                r_tx_busy   <= 1'b0     ;
                r_tx_done   <= 1'b0     ;

            end

        endcase

    end

end



// output

assign o_tx      = r_tx      ;
assign o_tx_busy = r_tx_busy ;
assign o_tx_done = r_tx_done ;

endmodule

proj1_make/TOP/SIM/TESTBENCH/tb_uart_tx.v
`timescale 1ns / 1ps

module tb_uart_tx;


// input

reg             clk         ;
reg             rst_n       ;

reg     [7:0]   i_tx_data   ;
reg             i_tx_start  ;


// output

wire            o_tx        ;
wire            o_tx_busy   ;
wire            o_tx_done   ;


// DUT

uart_tx #(
    .CLKS_PER_BIT(417)
)
u_uart_tx(
    .clk        (clk        ),
    .rst_n      (rst_n      ),

    .i_tx_data  (i_tx_data  ),
    .i_tx_start (i_tx_start ),

    .o_tx       (o_tx       ),
    .o_tx_busy  (o_tx_busy  ),
    .o_tx_done  (o_tx_done  )
);

// Dumpfile gen
`ifdef function_sim 
	initial begin
		$dumpfile("./dump/uart_tx.vcd")			;
		$dumpvars(0, tb_uart_tx)			;
	end
`endif

// 48 MHz clock
// 1 / 48 MHz = 20.833 ns

always begin

    #10.416
    clk = ~clk;

end


// stimulus

initial begin

    clk         = 1'b0;
    rst_n       = 1'b0;

    i_tx_data   = 8'h00;
    i_tx_start  = 1'b0;


    // reset

    #100;

    rst_n = 1'b1;


    // wait

    #100;


    // send ASCII 'A'
    // 8'h41 = 0100_0001

    @(posedge clk);

    i_tx_data  <= 8'h41;
    i_tx_start <= 1'b1;


    // tx_start = 1 for one clock

    @(posedge clk);

    i_tx_start <= 1'b0;


    // wait until transmission complete

    @(posedge o_tx_done);


    // some delay

    #1000;


    $finish;

end


endmodule

proj1_make/TOP/SIM/FUNCTION/dump/uart_tx.vcd
$date
    Sep 23, 2026  15:47:46
$end
$version
    TOOL:	xmsim(64)	22.03-s012
$end
$timescale
    1 ps
$end

$scope module tb_uart_tx $end
$var reg       1 !    clk $end
$var reg       1 "    rst_n $end
$var reg       8 #    i_tx_data [7:0] $end
$var reg       1 $    i_tx_start $end
$var wire      1 %    o_tx  $end
$var wire      1 &    o_tx_busy  $end
$var wire      1 '    o_tx_done  $end

$scope module u_uart_tx $end
$var wire      1 (    clk  $end
$var wire      1 )    rst_n  $end
$var wire      8 *    i_tx_data [7:0] $end
$var wire      1 +    i_tx_start  $end
$var wire      1 %    o_tx  $end
$var wire      1 &    o_tx_busy  $end
$var wire      1 '    o_tx_done  $end
$var parameter 32 ,    CLKS_PER_BIT $end
$var parameter  2 -    IDLE $end
$var parameter  2 .    START $end
$var parameter  2 /    DATA $end
$var parameter  2 0    STOP $end
$var reg       2 1    r_state [1:0] $end
$var reg       9 2    r_baud_cnt [8:0] $end
$var reg       3 3    r_bit_cnt [2:0] $end
$var reg       8 4    r_tx_data [7:0] $end
$var reg       1 5    r_tx $end
$var reg       1 6    r_tx_busy $end
$var reg       1 7    r_tx_done $end
$upscope $end

$upscope $end

$enddefinitions $end
$dumpvars
b11 0
b10 /
b1 .
b0 -
b110100001 ,
0!
0"
b0 #
0$
1%
0&
0'
0(
0)
b0 *
0+
b0 1
b0 2
b0 3
b0 4
15
06
07
$end
#10416
1!
1(
#20832
0!
0(
#31248
1!
1(
#41664
0!
0(
#52080
1!
1(
#62496
0!
0(
#72912
1!
1(
#83328
0!
0(
#93744
1!
1(
#100000
1"
1)
#104160
0!
0(
#114576
1!
1(
#124992
0!
0(
#135408
1!
1(
#145824
0!
0(
#156240
1!
1(
#166656
0!
0(
#177072
1!
1(
#187488
0!
0(
#197904
1!
1(
#208320
0!
0(
#218736
1!
1(
b1000001 #
1$
1+
b1000001 *
#229152
0!
0(
#239568
1!
1(
0$
b1000001 4
16
b1 1
0+
1&
#249984
0!
0(
#260400
1!
1(
05
b1 2
0%
#270816
0!
0(
#281232
1!
1(
b10 2
#291648
0!
0(
#302064
1!
1(
b11 2
#312480
0!
0(
#322896
1!
1(
b100 2
#333312
0!
0(
#343728
1!
1(
b101 2
#354144
0!
0(
#364560
1!
1(
b110 2
#374976
0!
0(
#385392
1!
1(
b111 2
#395808
0!
0(
#406224
1!
1(
b1000 2
#416640
0!
0(
#427056
1!
1(
b1001 2
#437472
0!
0(
#447888
1!
1(
b1010 2
#458304
0!
0(
#468720
1!
1(
b1011 2
#479136
0!
0(
#489552
1!
1(
b1100 2
#499968
0!
0(
#510384
1!
1(
b1101 2
#520800
0!
0(
#531216
1!
1(
b1110 2
#541632
0!
0(
#552048
1!
1(
b1111 2
#562464
0!
0(
#572880
1!
1(
b10000 2
#583296
0!
0(
#593712
1!
1(
b10001 2
#604128
0!
0(
#614544
1!
1(
b10010 2
#624960
0!
0(
#635376
1!
1(
b10011 2
#645792
0!
0(
#656208
1!
1(
b10100 2
#666624
0!
0(
#677040
1!
1(
b10101 2
#687456
0!
0(
#697872
1!
1(
b10110 2
#708288
0!
0(
#718704
1!
1(
b10111 2
#729120
0!
0(
#739536
1!
1(
b11000 2
#749952
0!
0(
#760368
1!
1(
b11001 2
#770784
0!
0(
#781200
1!
1(
b11010 2
#791616
0!
0(
#802032
1!
1(
b11011 2
#812448
0!
0(
#822864
1!
1(
b11100 2
#833280
0!
0(
#843696
1!
1(
b11101 2
#854112
0!
0(
#864528
1!
1(
b11110 2
#874944
0!
0(
#885360
1!
1(
b11111 2
#895776
0!
0(
#906192
1!
1(
b100000 2
#916608
0!
0(
#927024
1!
1(
b100001 2
#937440
0!
0(
#947856
1!
1(
b100010 2
#958272
0!
0(
#968688
1!
1(
b100011 2
#979104
0!
0(
#989520
1!
1(
b100100 2
#999936
0!
0(
#1010352
1!
1(
b100101 2
#1020768
0!
0(
#1031184
1!
1(
b100110 2
#1041600
0!
0(
#1052016
1!
1(
b100111 2
#1062432
0!
0(
#1072848
1!
1(
b101000 2
#1083264
0!
0(
#1093680
1!
1(
b101001 2
#1104096
0!
0(
#1114512
1!
1(
b101010 2
#1124928
0!
0(
#1135344
1!
1(
b101011 2
#1145760
0!
0(
#1156176
1!
1(
b101100 2
#1166592
0!
0(
#1177008
1!
1(
b101101 2
#1187424
0!
0(
#1197840
1!
1(
b101110 2
#1208256
0!
0(
#1218672
1!
1(
b101111 2
#1229088
0!
0(
#1239504
1!
1(
b110000 2
#1249920
0!
0(
#1260336
1!
1(
b110001 2
#1270752
0!
0(
#1281168
1!
1(
b110010 2
#1291584
0!
0(
#1302000
1!
1(
b110011 2
#1312416
0!
0(
#1322832
1!
1(
b110100 2
#1333248
0!
0(
#1343664
1!
1(
b110101 2
#1354080
0!
0(
#1364496
1!
1(
b110110 2
#1374912
0!
0(
#1385328
1!
1(
b110111 2
#1395744
0!
0(
#1406160
1!
1(
b111000 2
#1416576
0!
0(
#1426992
1!
1(
b111001 2
#1437408
0!
0(
#1447824
1!
1(
b111010 2
#1458240
0!
0(
#1468656
1!
1(
b111011 2
#1479072
0!
0(
#1489488
1!
1(
b111100 2
#1499904
0!
0(
#1510320
1!
1(
b111101 2
#1520736
0!
0(
#1531152
1!
1(
b111110 2
#1541568
0!
0(
#1551984
1!
1(
b111111 2
#1562400
0!
0(
#1572816
1!
1(
b1000000 2
#1583232
0!
0(
#1593648
1!
1(
b1000001 2
#1604064
0!
0(
#1614480
1!
1(
b1000010 2
#1624896
0!
0(
#1635312
1!
1(
b1000011 2
#1645728
0!
0(
#1656144
1!
1(
b1000100 2
#1666560
0!
0(
#1676976
1!
1(
b1000101 2
#1687392
0!
0(
#1697808
1!
1(
b1000110 2
#1708224
0!
0(
#1718640
1!
1(
b1000111 2
#1729056
0!
0(
#1739472
1!
1(
b1001000 2
#1749888
0!
0(
#1760304
1!
1(
b1001001 2
#1770720
0!
0(
#1781136
1!
1(
b1001010 2
#1791552
0!
0(
#1801968
1!
1(
b1001011 2
#1812384
0!
0(
#1822800
1!
1(
b1001100 2
#1833216
0!
0(
#1843632
1!
1(
b1001101 2
#1854048
0!
0(
#1864464
1!
1(
b1001110 2
#1874880
0!
0(
#1885296
1!
1(
b1001111 2
#1895712
0!
0(
#1906128
1!
1(
b1010000 2
#1916544
0!
0(
#1926960
1!
1(
b1010001 2
#1937376
0!
0(
#1947792
1!
1(
b1010010 2
#1958208
0!
0(
#1968624
1!
1(
b1010011 2
#1979040
0!
0(
#1989456
1!
1(
b1010100 2
#1999872
0!
0(
#2010288
1!
1(
b1010101 2
#2020704
0!
0(
#2031120
1!
1(
b1010110 2
#2041536
0!
0(
#2051952
1!
1(
b1010111 2
#2062368
0!
0(
#2072784
1!
1(
b1011000 2
#2083200
0!
0(
#2093616
1!
1(
b1011001 2
#2104032
0!
0(
#2114448
1!
1(
b1011010 2
#2124864
0!
0(
#2135280
1!
1(
b1011011 2
#2145696
0!
0(
#2156112
1!
1(
b1011100 2
#2166528
0!
0(
#2176944
1!
1(
b1011101 2
#2187360
0!
0(
#2197776
1!
1(
b1011110 2
#2208192
0!
0(
#2218608
1!
1(
b1011111 2
#2229024
0!
0(
#2239440
1!
1(
b1100000 2
#2249856
0!
0(
#2260272
1!
1(
b1100001 2
#2270688
0!
0(
#2281104
1!
1(
b1100010 2
#2291520
0!
0(
#2301936
1!
1(
b1100011 2
#2312352
0!
0(
#2322768
1!
1(
b1100100 2
#2333184
0!
0(
#2343600
1!
1(
b1100101 2
#2354016
0!
0(
#2364432
1!
1(
b1100110 2
#2374848
0!
0(
#2385264
1!
1(
b1100111 2
#2395680
0!
0(
#2406096
1!
1(
b1101000 2
#2416512
0!
0(
#2426928
1!
1(
b1101001 2
#2437344
0!
0(
#2447760
1!
1(
b1101010 2
#2458176
0!
0(
#2468592
1!
1(
b1101011 2
#2479008
0!
0(
#2489424
1!
1(
b1101100 2
#2499840
0!
0(
#2510256
1!
1(
b1101101 2
#2520672
0!
0(
#2531088
1!
1(
b1101110 2
#2541504
0!
0(
#2551920
1!
1(
b1101111 2
#2562336
0!
0(
#2572752
1!
1(
b1110000 2
#2583168
0!
0(
#2593584
1!
1(
b1110001 2
#2604000
0!
0(
#2614416
1!
1(
b1110010 2
#2624832
0!
0(
#2635248
1!
1(
b1110011 2
#2645664
0!
0(
#2656080
1!
1(
b1110100 2
#2666496
0!
0(
#2676912
1!
1(
b1110101 2
#2687328
0!
0(
#2697744
1!
1(
b1110110 2
#2708160
0!
0(
#2718576
1!
1(
b1110111 2
#2728992
0!
0(
#2739408
1!
1(
b1111000 2
#2749824
0!
0(
#2760240
1!
1(
b1111001 2
#2770656
0!
0(
#2781072
1!
1(
b1111010 2
#2791488
0!
0(
#2801904
1!
1(
b1111011 2
#2812320
0!
0(
#2822736
1!
1(
b1111100 2
#2833152
0!
0(
#2843568
1!
1(
b1111101 2
#2853984
0!
0(
#2864400
1!
1(
b1111110 2
#2874816
0!
0(
#2885232
1!
1(
b1111111 2
#2895648
0!
0(
#2906064
1!
1(
b10000000 2
#2916480
0!
0(
#2926896
1!
1(
b10000001 2
#2937312
0!
0(
#2947728
1!
1(
b10000010 2
#2958144
0!
0(
#2968560
1!
1(
b10000011 2
#2978976
0!
0(
#2989392
1!
1(
b10000100 2
#2999808
0!
0(
#3010224
1!
1(
b10000101 2
#3020640
0!
0(
#3031056
1!
1(
b10000110 2
#3041472
0!
0(
#3051888
1!
1(
b10000111 2
#3062304
0!
0(
#3072720
1!
1(
b10001000 2
#3083136
0!
0(
#3093552
1!
1(
b10001001 2
#3103968
0!
0(
#3114384
1!
1(
b10001010 2
#3124800
0!
0(
#3135216
1!
1(
b10001011 2
#3145632
0!
0(
#3156048
1!
1(
b10001100 2
#3166464
0!
0(
#3176880
1!
1(
b10001101 2
#3187296
0!
0(
#3197712
1!
1(
b10001110 2
#3208128
0!
0(
#3218544
1!
1(
b10001111 2
#3228960
0!
0(
#3239376
1!
1(
b10010000 2
#3249792
0!
0(
#3260208
1!
1(
b10010001 2
#3270624
0!
0(
#3281040
1!
1(
b10010010 2
#3291456
0!
0(
#3301872
1!
1(
b10010011 2
#3312288
0!
0(
#3322704
1!
1(
b10010100 2
#3333120
0!
0(
#3343536
1!
1(
b10010101 2
#3353952
0!
0(
#3364368
1!
1(
b10010110 2
#3374784
0!
0(
#3385200
1!
1(
b10010111 2
#3395616
0!
0(
#3406032
1!
1(
b10011000 2
#3416448
0!
0(
#3426864
1!
1(
b10011001 2
#3437280
0!
0(
#3447696
1!
1(
b10011010 2
#3458112
0!
0(
#3468528
1!
1(
b10011011 2
#3478944
0!
0(
#3489360
1!
1(
b10011100 2
#3499776
0!
0(
#3510192
1!
1(
b10011101 2
#3520608
0!
0(
#3531024
1!
1(
b10011110 2
#3541440
0!
0(
#3551856
1!
1(
b10011111 2
#3562272
0!
0(
#3572688
1!
1(
b10100000 2
#3583104
0!
0(
#3593520
1!
1(
b10100001 2
#3603936
0!
0(
#3614352
1!
1(
b10100010 2
#3624768
0!
0(
#3635184
1!
1(
b10100011 2
#3645600
0!
0(
#3656016
1!
1(
b10100100 2
#3666432
0!
0(
#3676848
1!
1(
b10100101 2
#3687264
0!
0(
#3697680
1!
1(
b10100110 2
#3708096
0!
0(
#3718512
1!
1(
b10100111 2
#3728928
0!
0(
#3739344
1!
1(
b10101000 2
#3749760
0!
0(
#3760176
1!
1(
b10101001 2
#3770592
0!
0(
#3781008
1!
1(
b10101010 2
#3791424
0!
0(
#3801840
1!
1(
b10101011 2
#3812256
0!
0(
#3822672
1!
1(
b10101100 2
#3833088
0!
0(
#3843504
1!
1(
b10101101 2
#3853920
0!
0(
#3864336
1!
1(
b10101110 2
#3874752
0!
0(
#3885168
1!
1(
b10101111 2
#3895584
0!
0(
#3906000
1!
1(
b10110000 2
#3916416
0!
0(
#3926832
1!
1(
b10110001 2
#3937248
0!
0(
#3947664
1!
1(
b10110010 2
#3958080
0!
0(
#3968496
1!
1(
b10110011 2
#3978912
0!
0(
#3989328
1!
1(
b10110100 2
#3999744
0!
0(
#4010160
1!
1(
b10110101 2
#4020576
0!
0(
#4030992
1!
1(
b10110110 2
#4041408
0!
0(
#4051824
1!
1(
b10110111 2
#4062240
0!
0(
#4072656
1!
1(
b10111000 2
#4083072
0!
0(
#4093488
1!
1(
b10111001 2
#4103904
0!
0(
#4114320
1!
1(
b10111010 2
#4124736
0!
0(
#4135152
1!
1(
b10111011 2
#4145568
0!
0(
#4155984
1!
1(
b10111100 2
#4166400
0!
0(
#4176816
1!
1(
b10111101 2
#4187232
0!
0(
#4197648
1!
1(
b10111110 2
#4208064
0!
0(
#4218480
1!
1(
b10111111 2
#4228896
0!
0(
#4239312
1!
1(
b11000000 2
#4249728
0!
0(
#4260144
1!
1(
b11000001 2
#4270560
0!
0(
#4280976
1!
1(
b11000010 2
#4291392
0!
0(
#4301808
1!
1(
b11000011 2
#4312224
0!
0(
#4322640
1!
1(
b11000100 2
#4333056
0!
0(
#4343472
1!
1(
b11000101 2
#4353888
0!
0(
#4364304
1!
1(
b11000110 2
#4374720
0!
0(
#4385136
1!
1(
b11000111 2
#4395552
0!
0(
#4405968
1!
1(
b11001000 2
#4416384
0!
0(
#4426800
1!
1(
b11001001 2
#4437216
0!
0(
#4447632
1!
1(
b11001010 2
#4458048
0!
0(
#4468464
1!
1(
b11001011 2
#4478880
0!
0(
#4489296
1!
1(
b11001100 2
#4499712
0!
0(
#4510128
1!
1(
b11001101 2
#4520544
0!
0(
#4530960
1!
1(
b11001110 2
#4541376
0!
0(
#4551792
1!
1(
b11001111 2
#4562208
0!
0(
#4572624
1!
1(
b11010000 2
#4583040
0!
0(
#4593456
1!
1(
b11010001 2
#4603872
0!
0(
#4614288
1!
1(
b11010010 2
#4624704
0!
0(
#4635120
1!
1(
b11010011 2
#4645536
0!
0(
#4655952
1!
1(
b11010100 2
#4666368
0!
0(
#4676784
1!
1(
b11010101 2
#4687200
0!
0(
#4697616
1!
1(
b11010110 2
#4708032
0!
0(
#4718448
1!
1(
b11010111 2
#4728864
0!
0(
#4739280
1!
1(
b11011000 2
#4749696
0!
0(
#4760112
1!
1(
b11011001 2
#4770528
0!
0(
#4780944
1!
1(
b11011010 2
#4791360
0!
0(
#4801776
1!
1(
b11011011 2
#4812192
0!
0(
#4822608
1!
1(
b11011100 2
#4833024
0!
0(
#4843440
1!
1(
b11011101 2
#4853856
0!
0(
#4864272
1!
1(
b11011110 2
#4874688
0!
0(
#4885104
1!
1(
b11011111 2
#4895520
0!
0(
#4905936
1!
1(
b11100000 2
#4916352
0!
0(
#4926768
1!
1(
b11100001 2
#4937184
0!
0(
#4947600
1!
1(
b11100010 2
#4958016
0!
0(
#4968432
1!
1(
b11100011 2
#4978848
0!
0(
#4989264
1!
1(
b11100100 2
#4999680
0!
0(
#5010096
1!
1(
b11100101 2
#5020512
0!
0(
#5030928
1!
1(
b11100110 2
#5041344
0!
0(
#5051760
1!
1(
b11100111 2
#5062176
0!
0(
#5072592
1!
1(
b11101000 2
#5083008
0!
0(
#5093424
1!
1(
b11101001 2
#5103840
0!
0(
#5114256
1!
1(
b11101010 2
#5124672
0!
0(
#5135088
1!
1(
b11101011 2
#5145504
0!
0(
#5155920
1!
1(
b11101100 2
#5166336
0!
0(
#5176752
1!
1(
b11101101 2
#5187168
0!
0(
#5197584
1!
1(
b11101110 2
#5208000
0!
0(
#5218416
1!
1(
b11101111 2
#5228832
0!
0(
#5239248
1!
1(
b11110000 2
#5249664
0!
0(
#5260080
1!
1(
b11110001 2
#5270496
0!
0(
#5280912
1!
1(
b11110010 2
#5291328
0!
0(
#5301744
1!
1(
b11110011 2
#5312160
0!
0(
#5322576
1!
1(
b11110100 2
#5332992
0!
0(
#5343408
1!
1(
b11110101 2
#5353824
0!
0(
#5364240
1!
1(
b11110110 2
#5374656
0!
0(
#5385072
1!
1(
b11110111 2
#5395488
0!
0(
#5405904
1!
1(
b11111000 2
#5416320
0!
0(
#5426736
1!
1(
b11111001 2
#5437152
0!
0(
#5447568
1!
1(
b11111010 2
#5457984
0!
0(
#5468400
1!
1(
b11111011 2
#5478816
0!
0(
#5489232
1!
1(
b11111100 2
#5499648
0!
0(
#5510064
1!
1(
b11111101 2
#5520480
0!
0(
#5530896
1!
1(
b11111110 2
#5541312
0!
0(
#5551728
1!
1(
b11111111 2
#5562144
0!
0(
#5572560
1!
1(
b100000000 2
#5582976
0!
0(
#5593392
1!
1(
b100000001 2
#5603808
0!
0(
#5614224
1!
1(
b100000010 2
#5624640
0!
0(
#5635056
1!
1(
b100000011 2
#5645472
0!
0(
#5655888
1!
1(
b100000100 2
#5666304
0!
0(
#5676720
1!
1(
b100000101 2
#5687136
0!
0(
#5697552
1!
1(
b100000110 2
#5707968
0!
0(
#5718384
1!
1(
b100000111 2
#5728800
0!
0(
#5739216
1!
1(
b100001000 2
#5749632
0!
0(
#5760048
1!
1(
b100001001 2
#5770464
0!
0(
#5780880
1!
1(
b100001010 2
#5791296
0!
0(
#5801712
1!
1(
b100001011 2
#5812128
0!
0(
#5822544
1!
1(
b100001100 2
#5832960
0!
0(
#5843376
1!
1(
b100001101 2
#5853792
0!
0(
#5864208
1!
1(
b100001110 2
#5874624
0!
0(
#5885040
1!
1(
b100001111 2
#5895456
0!
0(
#5905872
1!
1(
b100010000 2
#5916288
0!
0(
#5926704
1!
1(
b100010001 2
#5937120
0!
0(
#5947536
1!
1(
b100010010 2
#5957952
0!
0(
#5968368
1!
1(
b100010011 2
#5978784
0!
0(
#5989200
1!
1(
b100010100 2
#5999616
0!
0(
#6010032
1!
1(
b100010101 2
#6020448
0!
0(
#6030864
1!
1(
b100010110 2
#6041280
0!
0(
#6051696
1!
1(
b100010111 2
#6062112
0!
0(
#6072528
1!
1(
b100011000 2
#6082944
0!
0(
#6093360
1!
1(
b100011001 2
#6103776
0!
0(
#6114192
1!
1(
b100011010 2
#6124608
0!
0(
#6135024
1!
1(
b100011011 2
#6145440
0!
0(
#6155856
1!
1(
b100011100 2
#6166272
0!
0(
#6176688
1!
1(
b100011101 2
#6187104
0!
0(
#6197520
1!
1(
b100011110 2
#6207936
0!
0(
#6218352
1!
1(
b100011111 2
#6228768
0!
0(
#6239184
1!
1(
b100100000 2
#6249600
0!
0(
#6260016
1!
1(
b100100001 2
#6270432
0!
0(
#6280848
1!
1(
b100100010 2
#6291264
0!
0(
#6301680
1!
1(
b100100011 2
#6312096
0!
0(
#6322512
1!
1(
b100100100 2
#6332928
0!
0(
#6343344
1!
1(
b100100101 2
#6353760
0!
0(
#6364176
1!
1(
b100100110 2
#6374592
0!
0(
#6385008
1!
1(
b100100111 2
#6395424
0!
0(
#6405840
1!
1(
b100101000 2
#6416256
0!
0(
#6426672
1!
1(
b100101001 2
#6437088
0!
0(
#6447504
1!
1(
b100101010 2
#6457920
0!
0(
#6468336
1!
1(
b100101011 2
#6478752
0!
0(
#6489168
1!
1(
b100101100 2
#6499584
0!
0(
#6510000
1!
1(
b100101101 2
#6520416
0!
0(
#6530832
1!
1(
b100101110 2
#6541248
0!
0(
#6551664
1!
1(
b100101111 2
#6562080
0!
0(
#6572496
1!
1(
b100110000 2
#6582912
0!
0(
#6593328
1!
1(
b100110001 2
#6603744
0!
0(
#6614160
1!
1(
b100110010 2
#6624576
0!
0(
#6634992
1!
1(
b100110011 2
#6645408
0!
0(
#6655824
1!
1(
b100110100 2
#6666240
0!
0(
#6676656
1!
1(
b100110101 2
#6687072
0!
0(
#6697488
1!
1(
b100110110 2
#6707904
0!
0(
#6718320
1!
1(
b100110111 2
#6728736
0!
0(
#6739152
1!
1(
b100111000 2
#6749568
0!
0(
#6759984
1!
1(
b100111001 2
#6770400
0!
0(
#6780816
1!
1(
b100111010 2
#6791232
0!
0(
#6801648
1!
1(
b100111011 2
#6812064
0!
0(
#6822480
1!
1(
b100111100 2
#6832896
0!
0(
#6843312
1!
1(
b100111101 2
#6853728
0!
0(
#6864144
1!
1(
b100111110 2
#6874560
0!
0(
#6884976
1!
1(
b100111111 2
#6895392
0!
0(
#6905808
1!
1(
b101000000 2
#6916224
0!
0(
#6926640
1!
1(
b101000001 2
#6937056
0!
0(
#6947472
1!
1(
b101000010 2
#6957888
0!
0(
#6968304
1!
1(
b101000011 2
#6978720
0!
0(
#6989136
1!
1(
b101000100 2
#6999552
0!
0(
#7009968
1!
1(
b101000101 2
#7020384
0!
0(
#7030800
1!
1(
b101000110 2
#7041216
0!
0(
#7051632
1!
1(
b101000111 2
#7062048
0!
0(
#7072464
1!
1(
b101001000 2
#7082880
0!
0(
#7093296
1!
1(
b101001001 2
#7103712
0!
0(
#7114128
1!
1(
b101001010 2
#7124544
0!
0(
#7134960
1!
1(
b101001011 2
#7145376
0!
0(
#7155792
1!
1(
b101001100 2
#7166208
0!
0(
#7176624
1!
1(
b101001101 2
#7187040
0!
0(
#7197456
1!
1(
b101001110 2
#7207872
0!
0(
#7218288
1!
1(
b101001111 2
#7228704
0!
0(
#7239120
1!
1(
b101010000 2
#7249536
0!
0(
#7259952
1!
1(
b101010001 2
#7270368
0!
0(
#7280784
1!
1(
b101010010 2
#7291200
0!
0(
#7301616
1!
1(
b101010011 2
#7312032
0!
0(
#7322448
1!
1(
b101010100 2
#7332864
0!
0(
#7343280
1!
1(
b101010101 2
#7353696
0!
0(
#7364112
1!
1(
b101010110 2
#7374528
0!
0(
#7384944
1!
1(
b101010111 2
#7395360
0!
0(
#7405776
1!
1(
b101011000 2
#7416192
0!
0(
#7426608
1!
1(
b101011001 2
#7437024
0!
0(
#7447440
1!
1(
b101011010 2
#7457856
0!
0(
#7468272
1!
1(
b101011011 2
#7478688
0!
0(
#7489104
1!
1(
b101011100 2
#7499520
0!
0(
#7509936
1!
1(
b101011101 2
#7520352
0!
0(
#7530768
1!
1(
b101011110 2
#7541184
0!
0(
#7551600
1!
1(
b101011111 2
#7562016
0!
0(
#7572432
1!
1(
b101100000 2
#7582848
0!
0(
#7593264
1!
1(
b101100001 2
#7603680
0!
0(
#7614096
1!
1(
b101100010 2
#7624512
0!
0(
#7634928
1!
1(
b101100011 2
#7645344
0!
0(
#7655760
1!
1(
b101100100 2
#7666176
0!
0(
#7676592
1!
1(
b101100101 2
#7687008
0!
0(
#7697424
1!
1(
b101100110 2
#7707840
0!
0(
#7718256
1!
1(
b101100111 2
#7728672
0!
0(
#7739088
1!
1(
b101101000 2
#7749504
0!
0(
#7759920
1!
1(
b101101001 2
#7770336
0!
0(
#7780752
1!
1(
b101101010 2
#7791168
0!
0(
#7801584
1!
1(
b101101011 2
#7812000
0!
0(
#7822416
1!
1(
b101101100 2
#7832832
0!
0(
#7843248
1!
1(
b101101101 2
#7853664
0!
0(
#7864080
1!
1(
b101101110 2
#7874496
0!
0(
#7884912
1!
1(
b101101111 2
#7895328
0!
0(
#7905744
1!
1(
b101110000 2
#7916160
0!
0(
#7926576
1!
1(
b101110001 2
#7936992
0!
0(
#7947408
1!
1(
b101110010 2
#7957824
0!
0(
#7968240
1!
1(
b101110011 2
#7978656
0!
0(
#7989072
1!
1(
b101110100 2
#7999488
0!
0(
#8009904
1!
1(
b101110101 2
#8020320
0!
0(
#8030736
1!
1(
b101110110 2
#8041152
0!
0(
#8051568
1!
1(
b101110111 2
#8061984
0!
0(
#8072400
1!
1(
b101111000 2
#8082816
0!
0(
#8093232
1!
1(
b101111001 2
#8103648
0!
0(
#8114064
1!
1(
b101111010 2
#8124480
0!
0(
#8134896
1!
1(
b101111011 2
#8145312
0!
0(
#8155728
1!
1(
b101111100 2
#8166144
0!
0(
#8176560
1!
1(
b101111101 2
#8186976
0!
0(
#8197392
1!
1(
b101111110 2
#8207808
0!
0(
#8218224
1!
1(
b101111111 2
#8228640
0!
0(
#8239056
1!
1(
b110000000 2
#8249472
0!
0(
#8259888
1!
1(
b110000001 2
#8270304
0!
0(
#8280720
1!
1(
b110000010 2
#8291136
0!
0(
#8301552
1!
1(
b110000011 2
#8311968
0!
0(
#8322384
1!
1(
b110000100 2
#8332800
0!
0(
#8343216
1!
1(
b110000101 2
#8353632
0!
0(
#8364048
1!
1(
b110000110 2
#8374464
0!
0(
#8384880
1!
1(
b110000111 2
#8395296
0!
0(
#8405712
1!
1(
b110001000 2
#8416128
0!
0(
#8426544
1!
1(
b110001001 2
#8436960
0!
0(
#8447376
1!
1(
b110001010 2
#8457792
0!
0(
#8468208
1!
1(
b110001011 2
#8478624
0!
0(
#8489040
1!
1(
b110001100 2
#8499456
0!
0(
#8509872
1!
1(
b110001101 2
#8520288
0!
0(
