proj1_make/TOP/RTL/usr_4bit.v
`timescale 1ns / 1ps

module usr_4bit(
	//port list
	clk		,
	rst_n		,
	i_parallel	,
	i_shift_l	,
	i_shift_r	,
	i_mode		,
	o_data
);
//port declaration
input		clk		;
input		rst_n		;
input	[3:0]	i_parallel	;
input		i_shift_l	;
input		i_shift_r	;
input	[1:0]	i_mode		;
output	[3:0]	o_data		;

//internal register
reg	[3:0]	r_data		;


//modeling
always @(posedge clk or negedge rst_n) begin
	if( ~rst_n ) r_data  <= 4'b0000		;
	else begin
		case ( i_mode )
			2'b00 	: r_data <= r_data			;	// hold,  [d, c, b, a]
			2'b01 	: r_data <= {r_data[2:0], i_shift_r}	;	// shift right, from lsb to msb,  [c, b, a, sr]
			2'b10 	: r_data <= {i_shift_l, r_data[3:1]}	;	// shift left, from msb to lsb, [sl, d, c, b]
			2'b11 	: r_data <= i_parallel			;	// output
			default : r_data <= r_data			;
		endcase
	end
end

assign o_data = r_data	;

endmodule

proj1_make/TOP/SIM/TESTBENCH/tb_usr_4bit.v
`timescale 1ns / 1ps

module tb_usr_4bit;
//signal def
//stimulus signal
reg		clk		;
reg		rst_n		;
reg	[3:0]	i_parallel	;
reg		i_shift_l	;
reg		i_shift_r	;
reg	[1:0]	i_mode		;
//monitoring sigal
wire	[3:0]	o_data		;

//DUT instantiation
usr_4bit dut (
	.clk		(clk		)	,
	.rst_n		(rst_n		)	,
	.i_parallel	(i_parallel	)	,
	.i_shift_l	(i_shift_l	)	,
	.i_shift_r	(i_shift_r	)	,
	.i_mode		(i_mode		)	,
	.o_data		(o_data		)
);

//dumpfile gen
initial begin
	$dumpfile("./usr_4bit.vcd"	)	;
	$dumpvars(0, tb_usr_4bit	)	;
end

//clk gen
always #5 clk = ~clk;

//test scenario
initial begin
	//t=0, init
	clk = 1'b0;	rst_n = 1'b0;
	i_parallel = 4'b0000;
	i_shift_l = 1'b0;	i_shift_r = 1'b0;
	i_mode = 2'b00;

	//rst release
	#20 rst_n = 1'b1;
	
	@(negedge clk);
	i_parallel = 4'b1011;
	i_mode = 2'b11;

	@(negedge clk);
	i_mode = 2'b00;

	@(negedge clk);
	i_shift_r = 1'b0;
	i_mode = 2'b01;

	@(negedge clk);
	i_shift_r = 1'b1;
	i_mode = 2'b01;

	@(negedge clk);
	i_shift_l = 1'b0;
	i_mode = 2'b10;

	@(negedge clk);
	i_shift_l = 1'b0;
	i_mode = 2'b10;

	@(negedge clk);
	rst_n = 1'b0;

	#50; $finish;
end

endmodule

proj1_make/TOP/SIM/FUNCTION/usr_4bit.vcd
$date
    Sep 23, 2026  01:24:52
$end
$version
    TOOL:	xmsim(64)	22.03-s012
$end
$timescale
    1 ps
$end

$scope module tb_usr_4bit $end
$var reg       1 !    clk $end
$var reg       1 "    rst_n $end
$var reg       4 #    i_parallel [3:0] $end
$var reg       1 $    i_shift_l $end
$var reg       1 %    i_shift_r $end
$var reg       2 &    i_mode [1:0] $end
$var wire      4 '    o_data [3:0] $end

$scope module dut $end
$var wire      1 (    clk  $end
$var wire      1 )    rst_n  $end
$var wire      4 *    i_parallel [3:0] $end
$var wire      1 +    i_shift_l  $end
$var wire      1 ,    i_shift_r  $end
$var wire      2 -    i_mode [1:0] $end
$var wire      4 '    o_data [3:0] $end
$var reg       4 .    r_data [3:0] $end
$upscope $end

$upscope $end

$enddefinitions $end
$dumpvars
0!
0"
b0 #
0$
0%
b0 &
b0 '
0(
0)
b0 *
0+
0,
b0 -
b0 .
$end
#5000
1!
1(
#10000
0!
0(
#15000
1!
1(
#20000
1"
0!
b1011 #
b11 &
b11 -
b1011 *
0(
1)
#25000
1!
1(
b1011 .
b1011 '
#30000
0!
b0 &
b0 -
0(
#35000
1!
1(
#40000
0!
b1 &
b1 -
0(
#45000
1!
1(
b110 .
b110 '
#50000
0!
1%
1,
0(
#55000
1!
1(
b1101 .
b1101 '
#60000
0!
b10 &
b10 -
0(
#65000
1!
1(
b110 .
b110 '
#70000
0!
0(
#75000
1!
1(
b11 .
b11 '
#80000
0!
0"
0)
0(
b0 .
b0 '
